poetry_githooks/__init__.py
poetry_githooks/helpers.py
poetry_githooks/hooks.py
poetry_githooks/settings.py
poetry_githooks-3.0.1.dist-info/LICENSE
poetry_githooks-3.0.1.dist-info/METADATA
poetry_githooks-3.0.1.dist-info/WHEEL
poetry_githooks-3.0.1.dist-info/entry_points.txt
poetry_githooks-3.0.1.dist-info/RECORD
