Metadata-Version: 2.1
Name: poetry-githooks
Version: 3.0.1
Summary: Simple git hooks with poetry
Home-page: https://github.com/thomasthiebaud/poetry-githooks
License: MIT
Keywords: git,hook,githooks,poetry
Author: Thomas Thiebaud
Author-email: thiebaud.tom@gmail.com
Requires-Python: >=3.8,<4.0
Classifier: Development Status :: 4 - Beta
Classifier: Intended Audience :: Developers
Classifier: License :: OSI Approved :: MIT License
Classifier: Operating System :: OS Independent
Classifier: Programming Language :: Python :: 3
Classifier: Programming Language :: Python :: 3.8
Classifier: Programming Language :: Python :: 3.9
Classifier: Programming Language :: Python :: 3.10
Classifier: Programming Language :: Python :: 3.11
Classifier: Programming Language :: Python :: 3.12
Classifier: Topic :: Scientific/Engineering
Classifier: Topic :: Software Development
Requires-Dist: click (>=8.1.6,<9.0.0)
Requires-Dist: toml (>=0.10.2,<0.11.0)
Project-URL: Documentation, https://github.com/thomasthiebaud/poetry-githooks
Project-URL: Repository, https://github.com/thomasthiebaud/poetry-githooks
